LICENSE
MANIFEST.in
README.md
setup.cfg
setup.py
rhodb/__init__.py
rhodb/arangodb.py
rhodb/aws.py
rhodb/compat.py
rhodb/database.py
rhodb/elasticsearch.py
rhodb/flask_sqlalchemy.py
rhodb/redis_conf.py
rhodb/rhodb_sqlalchemy.py
rhodb/utils.py
rhodb.egg-info/PKG-INFO
rhodb.egg-info/SOURCES.txt
rhodb.egg-info/dependency_links.txt
rhodb.egg-info/requires.txt
rhodb.egg-info/top_level.txt
tests/fixtures/__init__.py
tests/fixtures/app_fixtures.py
tests/fixtures/mocks.py