Metadata-Version: 2.1
Name: rhodb
Version: 6.0.0
Summary: Rho AI Database Helpers
Home-page: https://gitlab.com/sermos/rho-db
Maintainer: Rho AI
License: MIT
Platform: UNKNOWN
Provides-Extra: sqlalchemy
Provides-Extra: flask_sqlalchemy
Provides-Extra: redis
Provides-Extra: aws
Provides-Extra: elasticsearch
Provides-Extra: arangodb
Provides-Extra: dev
Provides-Extra: test
License-File: LICENSE
